Metadata-Version: 2.1
Name: word-def
Version: 0.2.0
Summary: Get definition of words in any language
Author-email: Daniel Martins Antunes <danoan2008@gmail.com>
License: MIT License
Project-URL: Documentation, https://github.com/danoan/word-def#readme
Project-URL: Issues, https://github.com/danoan/word-def
Project-URL: Source, https://github.com/danoan/word-def
Classifier: Development Status :: 4 - Beta
Classifier: Programming Language :: Python
Classifier: Programming Language :: Python :: 3.8
Classifier: Programming Language :: Python :: Implementation :: CPython
Classifier: Programming Language :: Python :: Implementation :: PyPy
Requires-Python: >=3.8
License-File: LICENSE.txt
